{
  "meta_title": "",
  "meta_description": "",
  "sections": [
    {
      "type": "banner-slider",
      "autoplay": 9000,
      "full_width": false,
      "slides": [
        {
          "start": "",
          "end": "",
          "img": "/img/uploads/795ad744-cbe2-4293-91c0-b7445a1d9a89.png"
        }
      ]
    },
    {
      "type": "info-bar",
      "enabled": true
    },
    {
      "type": "collection-shelf",
      "shuffle": true,
      "collection_id": "624d911b2e405e04ff27204b:categories:vestidos :/vestidos",
      "sort": "news",
      "title": "Vem no nosso mar de verão ⛵️☀️🌿",
      "headless": false,
      "limit": 12,
      "page": 1
    },
    {
      "type": "dynamic-showcase",
      "load_more": true,
      "sort": "offers"
    }
  ]
}